{
	"instance" : {
		"evaluateFileNamed:" : "RonieSalgado 12/23/2017 21:59",
		"evaluateSource:name:" : "RonieSalgado 12/23/2017 21:59",
		"evaluateFileNamed:inContext:" : "RonieSalgado 12/23/2017 21:58",
		"evaluateSource:" : "RonieSalgado 12/23/2017 21:58",
		"compilationTarget" : "RonieSalgado 12/23/2017 22:07",
		"moduleScope" : "RonieSalgado 12/23/2017 23:06",
		"globalNamespace" : "RonieSalgado 12/24/2017 21:03",
		"topLevelScope" : "RonieSalgado 12/23/2017 23:06",
		"newEvaluationEnvironment" : "RonieSalgado 12/23/2017 21:59",
		"evaluateSource:name:inContext:" : "RonieSalgado 12/25/2017 23:03",
		"convertParseFailure:collection:" : "RonieSalgado 12/23/2017 21:51",
		"initializeWithCompilationTarget:" : "RonieSalgado 12/23/2017 22:56"
	},
	"class" : {
		"new" : "RonieSalgado 12/23/2017 20:56",
		"x86" : "RonieSalgado 12/23/2017 21:08",
		"x86_64" : "RonieSalgado 12/23/2017 21:09",
		"for:" : "RonieSalgado 12/23/2017 21:08",
		"forCurrentImage" : "RonieSalgado 12/23/2017 21:09",
		"compilationTarget:" : "RonieSalgado 12/23/2017 20:56"
	}
}